aioamazondevices/__init__.py
aioamazondevices/api.py
aioamazondevices/const/__init__.py
aioamazondevices/const/devices.py
aioamazondevices/const/http.py
aioamazondevices/const/metadata.py
aioamazondevices/const/queries.py
aioamazondevices/const/schedules.py
aioamazondevices/const/sounds.py
aioamazondevices/exceptions.py
aioamazondevices/http_wrapper.py
aioamazondevices/implementation/__init__.py
aioamazondevices/implementation/dnd.py
aioamazondevices/implementation/notification.py
aioamazondevices/implementation/sequence.py
aioamazondevices/login.py
aioamazondevices/py.typed
aioamazondevices/structures.py
aioamazondevices/utils.py
aioamazondevices-11.1.1.dist-info/METADATA
aioamazondevices-11.1.1.dist-info/WHEEL
aioamazondevices-11.1.1.dist-info/licenses/LICENSE
aioamazondevices-11.1.1.dist-info/RECORD
