Metadata-Version: 2.4
Name: aioamazondevices
Version: 11.1.1
Summary: Python library to control Amazon devices
License-Expression: Apache-2.0
License-File: LICENSE
Author: Simone Chemelli
Author-email: simone.chemelli@gmail.com
Requires-Python: >=3.12
Classifier: Development Status :: 4 - Beta
Classifier: Intended Audience :: Developers
Classifier: Natural Language :: English
Classifier: Operating System :: OS Independent
Classifier: Topic :: Software Development :: Libraries
Requires-Dist: aiohttp (>=3.12.7)
Requires-Dist: beautifulsoup4
Requires-Dist: colorlog
Requires-Dist: langcodes
Requires-Dist: orjson (>=3.10,<4)
Requires-Dist: python-dateutil
Project-URL: Bug Tracker, https://github.com/chemelli74/aioamazondevices/issues
Project-URL: Changelog, https://github.com/chemelli74/aioamazondevices/blob/main/CHANGELOG.md
Project-URL: Homepage, https://github.com/chemelli74/aioamazondevices
